shruby/__init__.py
shruby/lib/__init__.py
shruby/lib/utils.py
shruby-0.1.0.dist-info/METADATA
shruby-0.1.0.dist-info/WHEEL
shruby-0.1.0.dist-info/RECORD
