Metadata-Version: 2.1
Name: shruby
Version: 0.1.0
Summary: A wrapper for ArcGIS API and GeoPandas DataFrame that adds a simple API to repetitive processes used in GIS calculations.
Author: msherburne
Requires-Python: >=3.9,<3.12
Classifier: Programming Language :: Python :: 3
Classifier: Programming Language :: Python :: 3.9
Classifier: Programming Language :: Python :: 3.10
Classifier: Programming Language :: Python :: 3.11
Requires-Dist: arcgis (>=2.2.0.1,<3.0.0.0)
Requires-Dist: geopandas (>=0.14.1,<0.15.0)
Requires-Dist: gssapi (>=1.8.3,<2.0.0)
Requires-Dist: numpy (>=1.26.2,<2.0.0)
Requires-Dist: pandas (>=2.1.3,<3.0.0)
Requires-Dist: pyproj (>=3.6.1,<4.0.0)
Requires-Dist: shapely (>=2.0.2,<3.0.0)
